{
  "eaecb54c-0fb4-4736-8bf5-091f9ab2b091": {
    "instanceID": "eaecb54c-0fb4-4736-8bf5-091f9ab2b091",
    "lastTimePulled": {
      "activity": 1426485375000,
      "comment": 1,
      "jivecomment": 1
    }
  },
  "edfeedeb-f0c7-4c93-9088-03f2cc85a281": {
    "instanceID": "edfeedeb-f0c7-4c93-9088-03f2cc85a281",
    "lastTimePulled": {
      "activity": 1426493517000,
      "comment": 1426596178000,
      "jivecomment": 1426595720930
    },
    "syncs": [
      "0D7j0000000ZbQNCA0"
    ]
  },
  "63e1db31-01ed-459e-807f-be9a046f14c0": {
    "instanceID": "63e1db31-01ed-459e-807f-be9a046f14c0",
    "lastTimePulled": {
      "activity": 1426493517000,
      "comment": 1426596178000,
      "jivecomment": 1426490406236
    },
    "syncs": [
      "0D7j0000000ZY2KCAW"
    ]
  },
  "fcdcdc56-0efc-4fa0-be12-dc1eb15b7b4d": {
    "instanceID": "fcdcdc56-0efc-4fa0-be12-dc1eb15b7b4d",
    "lastTimePulled": {
      "activity": 1426493517000,
      "comment": 1426596178000,
      "jivecomment": 1
    }
  },
  "6e208b24-1bf3-4709-89c8-c669849fbdac": {
    "instanceID": "6e208b24-1bf3-4709-89c8-c669849fbdac",
    "lastTimePulled": {
      "activity": 1426598525000,
      "comment": 1426597397000,
      "jivecomment": 1426598597359
    },
    "syncs": [
      "0D7j0000000ZbSTCA0"
    ]
  }
}